visualobjecteditor/__init__.py
visualobjecteditor/base.py
visualobjecteditor/block.py
visualobjecteditor/line.py
visualobjecteditor/nested.py
visualobjecteditor/page.py
visualobjecteditor/table.py
visualobjecteditor/utils.py
visualobjecteditor-0.1.dist-info/METADATA
visualobjecteditor-0.1.dist-info/WHEEL
visualobjecteditor-0.1.dist-info/RECORD
