Metadata-Version: 2.1
Name: visualobjecteditor
Version: 0.1
Summary: Manipulate arbitrary objects with a text editor.
License: MIT
Author: Tomas Bayer
Author-email: mail@tomas.berlin
Requires-Python: >=3.9,<4.0
Classifier: License :: OSI Approved :: MIT License
Classifier: Programming Language :: Python :: 3
Classifier: Programming Language :: Python :: 3.9
Classifier: Programming Language :: Python :: 3.10
Classifier: Programming Language :: Python :: 3.11
Classifier: Programming Language :: Python :: 3.12
Requires-Dist: rich (>=13.7.0,<14.0.0)
Requires-Dist: tabulate (>=0.9.0,<0.10.0)
